hashtags/__init__.py
hashtags-1.9.dist-info/LICENSE
hashtags-1.9.dist-info/METADATA
hashtags-1.9.dist-info/WHEEL
hashtags-1.9.dist-info/top_level.txt
hashtags-1.9.dist-info/RECORD
