Metadata-Version: 2.1
Name: hashtags
Version: 1.9
Summary: A package to get best hashtags
Home-page: https://github.com/IndieD3v/hashtags-pypi
Author: In Dev
Author-email: tanmaymakode76@gmail.com
License: UNKNOWN
Platform: UNKNOWN
Classifier: Programming Language :: Python :: 3
Classifier: License :: OSI Approved :: MIT License
Classifier: Operating System :: OS Independent
Requires-Python: >=3.6
